easy_whisper/__init__.py
easy_whisper/__main__.py
easy_whisper/api_trans.py
easy_whisper/cli_ui.py
easy_whisper/tk_ui.py
easy_whisper/trans.py
easy_whisper/ui_share.py
easy_whisper-1.1.0.dist-info/LICENSE.txt
easy_whisper-1.1.0.dist-info/METADATA
easy_whisper-1.1.0.dist-info/WHEEL
easy_whisper-1.1.0.dist-info/entry_points.txt
easy_whisper-1.1.0.dist-info/top_level.txt
easy_whisper-1.1.0.dist-info/RECORD
