Metadata-Version: 2.1
Name: easy_whisper
Version: 1.1.0
Summary: An easy to use adaption of OpenAI's Whisper, with both CLI and (tkinter) GUI, faster processing even on CPU, txt output with timestamps.
Home-page: https://github.com/gyllila/easy_whisper
Author: Yanling Guo
Author-email: Yanling Guo <guoyanling_2000@yahoo.de>
Project-URL: Homepage, https://github.com/gyllila/easy_whisper
Keywords: audio,transcribe,translate,STT,easy,fast,CPU,CUDA
Classifier: Programming Language :: Python :: 3
Classifier: License :: OSI Approved :: GNU General Public License (GPL)
Classifier: Operating System :: OS Independent
Requires-Python: >=3.8
License-File: LICENSE.txt
Requires-Dist: openai
Requires-Dist: openai-whisper
